{
    "name": "gminer",
    "NVIDIA1": {
        "name": "NVIDIA1",
        "delay": "1",
        "prestart": [],
        "commands": {
            "cuckoo_cycle": "",
            "cuckaroom": "",
            "cuckatoo31": "",
            "cuckatoo32": "",
            "beamv2": "",
            "eaglesong": "",
            "ethash": "",
            "equihash_96/5": "",
            "equihash_192/7": "",
            "equihash_144/5": "",
            "equihash_210/9": "",
            "equihash_200/9": "",
            "equihash_125/4": "",
            "kawpow": "",
            "cuckaroo29-bfc": "",
            "beamhashv3": ""
        },
        "difficulty": {
            "cuckoo_cycle": "",
            "cuckaroom": "",
            "cuckatoo31": "",
            "cuckatoo32": "",
            "beamv2": "",
            "eaglesong": "",
            "ethash": "",
            "equihash_96/5": "",
            "equihash_192/7": "",
            "equihash_144/5": "",
            "equihash_210/9": "",
            "equihash_200/9": "",
            "equihash_125/4": "",
            "kawpow": "",
            "cuckaroo29-bfc": "",
            "beamhashv3": ""
        },
        "naming": {
            "cuckoo_cycle": "cuckoo_cycle",
            "cuckaroom": "cuckaroom",
            "cuckatoo31": "cuckatoo31",
            "cuckatoo32": "cuckatoo32",
            "beamv2": "beamv2",
            "ethash": "ethash",
            "eaglesong": "eaglesong",
            "equihash_96/5": "equihash_96/5",
            "equihash_192/7": "equihash_192/7",
            "equihash_144/5": "equihash_144/5",
            "equihash_210/9": "equihash_210/9",
            "equihash_200/9": "equihash_210/9",
            "equihash_125/4": "equihash_125/4",
            "kawpow": "kawpow",
            "cuckaroo29-bfc": "cuckaroo29-bfc",
            "beamhashv3": "beamhashv3"
        },
        "fee": {
            "cuckoo_cycle": 2,
            "cuckaroom": 2,
            "cuckatoo31": 2,
            "cuckatoo32": 2,
            "beamv2": 2,
            "ethash": 0.65,
            "eaglesong": 2,
            "equihash_96/5": 2,
            "equihash_192/7": 2,
            "equihash_144/5": 2,
            "equihash_210/9": 2,
            "equihash_200/9": 2,
            "equihash_125/4": 2,
            "kawpow": 2,
            "cuckaroo29-bfc": 2,
            "beamhashv3": 2
        }
    },
    "NVIDIA2": {
        "name": "NVIDIA2",
        "delay": "1",
        "prestart": [],
        "commands": {
            "cuckoo_cycle": "",
            "cuckaroom": "",
            "cuckatoo31": "",
            "cuckatoo32": "",
            "beamv2": "",
            "eaglesong": "",
            "ethash": "",
            "equihash_96/5": "",
            "equihash_192/7": "",
            "equihash_144/5": "",
            "equihash_210/9": "",
            "equihash_200/9": "",
            "equihash_125/4": "",
            "kawpow": "",
            "cuckaroo29-bfc": "",
            "beamhashv3": ""
        },
        "difficulty": {
            "cuckoo_cycle": "",
            "cuckaroom": "",
            "cuckatoo31": "",
            "cuckatoo32": "",
            "beamv2": "",
            "eaglesong": "",
            "ethash": "",
            "equihash_96/5": "",
            "equihash_192/7": "",
            "equihash_144/5": "",
            "equihash_210/9": "",
            "equihash_200/9": "",
            "equihash_125/4": "",
            "kawpow": "",
            "cuckaroo29-bfc": "",
            "beamhashv3": ""
        },
        "naming": {
            "cuckoo_cycle": "cuckoo_cycle",
            "cuckaroom": "cuckaroom",
            "cuckatoo31": "cuckatoo31",
            "cuckatoo32": "cuckatoo32",
            "beamv2": "beamv2",
            "ethash": "ethash",
            "eaglesong": "eaglesong",
            "equihash_96/5": "equihash_96/5",
            "equihash_192/7": "equihash_192/7",
            "equihash_144/5": "equihash_144/5",
            "equihash_210/9": "equihash_210/9",
            "equihash_200/9": "equihash_210/9",
            "equihash_125/4": "equihash_125/4",
            "kawpow": "kawpow",
            "cuckaroo29-bfc": "cuckaroo29-bfc",
            "beamhashv3": "beamhashv3"
        },
        "fee": {
            "cuckoo_cycle": 2,
            "cuckaroom": 2,
            "cuckatoo31": 2,
            "cuckatoo32": 2,
            "beamv2": 2,
            "ethash": 0.65,
            "eaglesong": 2,
            "equihash_96/5": 2,
            "equihash_192/7": 2,
            "equihash_144/5": 2,
            "equihash_210/9": 2,
            "equihash_200/9": 2,
            "equihash_125/4": 2,
            "kawpow": 2,
            "cuckaroo29-bfc": 2,
            "beamhashv3": 2
        }
    },
    "NVIDIA3": {
        "name": "NVIDIA3",
        "delay": "1",
        "prestart": [],
        "commands": {
            "cuckoo_cycle": "",
            "cuckaroom": "",
            "cuckatoo31": "",
            "cuckatoo32": "",
            "beamv2": "",
            "eaglesong": "",
            "ethash": "",
            "equihash_96/5": "",
            "equihash_192/7": "",
            "equihash_144/5": "",
            "equihash_210/9": "",
            "equihash_200/9": "",
            "equihash_125/4": "",
            "kawpow": "",
            "cuckaroo29-bfc": "",
            "beamhashv3": ""
        },
        "difficulty": {
            "cuckoo_cycle": "",
            "cuckaroom": "",
            "cuckatoo31": "",
            "cuckatoo32": "",
            "beamv2": "",
            "eaglesong": "",
            "ethash": "",
            "equihash_96/5": "",
            "equihash_192/7": "",
            "equihash_144/5": "",
            "equihash_210/9": "",
            "equihash_200/9": "",
            "equihash_125/4": "",
            "kawpow": "",
            "cuckaroo29-bfc": "",
            "beamhashv3": ""
        },
        "naming": {
            "cuckoo_cycle": "cuckoo_cycle",
            "cuckaroom": "cuckaroom",
            "cuckatoo31": "cuckatoo31",
            "cuckatoo32": "cuckatoo32",
            "beamv2": "beamv2",
            "ethash": "ethash",
            "eaglesong": "eaglesong",
            "equihash_96/5": "equihash_96/5",
            "equihash_192/7": "equihash_192/7",
            "equihash_144/5": "equihash_144/5",
            "equihash_210/9": "equihash_210/9",
            "equihash_200/9": "equihash_210/9",
            "equihash_125/4": "equihash_125/4",
            "kawpow": "kawpow",
            "cuckaroo29-bfc": "cuckaroo29-bfc",
            "beamhashv3": "beamhashv3"
        },
        "fee": {
            "cuckoo_cycle": 2,
            "cuckaroom": 2,
            "cuckatoo31": 2,
            "cuckatoo32": 2,
            "beamv2": 2,
            "ethash": 0.65,
            "eaglesong": 2,
            "equihash_96/5": 2,
            "equihash_192/7": 2,
            "equihash_144/5": 2,
            "equihash_210/9": 2,
            "equihash_200/9": 2,
            "equihash_125/4": 2,
            "kawpow": 2,
            "cuckaroo29-bfc": 2,
            "beamhashv3": 2
        }
   }
}
