{
    "name": "xmrig-a",
    "AMD1": {
        "name": "AMD1",
        "delay": "1",
        "prestart": [
            "export GPU_MAX_HEAP_SIZE=100",
            "export GPU_USE_SYNC_OBJECTS=1",
            "export GPU_SINGLE_ALLOC_PERCENT=100",
            "export GPU_MAX_ALLOC_PERCENT=100"
        ],
        "commands": {
            "kawpow": "",
            "random-arq": "",
            "randomx": ""
        },
        "difficulty": {
            "kawpow": "",
            "random-arq": "",
            "randomx": ""
        },
        "naming": {
            "kawpow": "kawpow",
            "random-arq": "rx/arq",
            "randomx": "rx/0"
        },
        "fee": {
            "kawpow": 1,
            "random-arq": 1,
            "randomx": 1
        }   
    }
}
